{
    "category": "chassis", 
    "name": "climate", 
    "getters": {
        "default": {}
    }, 
    "state": "all", 
    "api": {
        "intro": 2, 
        "update": 11
    }, 
    "identifier": {
        "lsb": 36, 
        "msb": 0
    }, 
    "properties": [
        {
            "description": "The inside temperature in celsius per IEEE 754 formatting", 
            "name_cased": "insideTemperature", 
            "size": 4, 
            "type": "float", 
            "id": 1, 
            "name": "inside_temperature"
        }, 
        {
            "description": "The outside temperature in celsius per IEEE 754 formatting", 
            "name_cased": "outsideTemperature", 
            "size": 4, 
            "type": "float", 
            "id": 2, 
            "name": "outside_temperature"
        }, 
        {
            "description": "The driver temperature setting in celsius per IEEE 754 formatting", 
            "name_cased": "driverTemperatureSetting", 
            "size": 4, 
            "type": "float", 
            "id": 3, 
            "name": "driver_temperature_setting"
        }, 
        {
            "description": "The passenger temperature setting in celsius per IEEE 754 formatting", 
            "name_cased": "passengerTemperatureSetting", 
            "size": 4, 
            "type": "float", 
            "id": 4, 
            "name": "passenger_temperature_setting"
        }, 
        {
            "type": "types.active_state", 
            "id": 5, 
            "name_cased": "hvacState", 
            "name": "hvac_state"
        }, 
        {
            "type": "types.active_state", 
            "id": 6, 
            "name_cased": "defoggingState", 
            "name": "defogging_state"
        }, 
        {
            "type": "types.active_state", 
            "id": 7, 
            "name_cased": "defrostingState", 
            "name": "defrosting_state"
        }, 
        {
            "type": "types.active_state", 
            "id": 8, 
            "name_cased": "ionisingState", 
            "name": "ionising_state"
        }, 
        {
            "description": "The defrosting temperature setting in celsius per IEEE 754 formatting", 
            "name_cased": "defrostingTemperatureSetting", 
            "size": 4, 
            "type": "float", 
            "id": 9, 
            "name": "defrosting_temperature_setting"
        }, 
        {
            "pretty_name": "HVAC weekday starting times", 
            "multiple": true, 
            "name": "hvac_weekday_starting_times", 
            "name_cased": "hvacWeekdayStartingTimes", 
            "type": "types.hvac_weekday_starting_time", 
            "id": 11
        }, 
        {
            "description": "The rear temperature in celsius per IEEE 754 formatting", 
            "name_cased": "rearTemperatureSetting", 
            "size": 4, 
            "type": "float", 
            "id": 12, 
            "name": "rear_temperature_setting"
        }
    ], 
    "setters": [
        {
            "mandatory": [
                11
            ], 
            "name": "change_starting_times"
        }, 
        {
            "mandatory": [
                5
            ], 
            "name": "start_stop_hvac"
        }, 
        {
            "mandatory": [
                6
            ], 
            "name": "start_stop_defogging"
        }, 
        {
            "mandatory": [
                7
            ], 
            "name": "start_stop_defrosting"
        }, 
        {
            "mandatory": [
                8
            ], 
            "name": "start_stop_ionising"
        }, 
        {
            "optional": [
                3, 
                4, 
                12
            ], 
            "name": "set_temperature_settings"
        }
    ]
}