{
    "category": "chassis", 
    "name": "rooftop_control", 
    "name_cased": "rooftopControl", 
    "getters": {
        "name": "get_rooftop_state"
    }, 
    "state": "all", 
    "api": {
        "intro": 3, 
        "update": 11
    }, 
    "identifier": {
        "lsb": 37, 
        "msb": 0
    }, 
    "properties": [
        {
            "description": "1.0 (100%) is opaque, 0.0 (0%) is transparent", 
            "name_cased": "dimming", 
            "name": "dimming", 
            "type": "types.percentage", 
            "id": 1, 
            "examples": [
                {
                    "hex": "3ff0000000000000", 
                    "description": "Rooftop is opaque (100%)", 
                    "value": 1.0
                }
            ]
        }, 
        {
            "description": "1.0 (100%) is fully open, 0.0 (0%) is closed", 
            "name_cased": "position", 
            "name": "position", 
            "type": "types.percentage", 
            "id": 2, 
            "examples": [
                {
                    "hex": "3fe0000000000000", 
                    "description": "Rooftop is half-open (50%)", 
                    "value": 0.5
                }
            ]
        }, 
        {
            "name": "convertible_roof_state", 
            "name_cased": "convertibleRoofState", 
            "enum_values": [
                {
                    "verb": "close", 
                    "id": 0, 
                    "name": "closed"
                }, 
                {
                    "id": 1, 
                    "name": "open"
                }, 
                {
                    "id": 2, 
                    "disabled_in_setter": true, 
                    "name": "emergency_locked"
                }, 
                {
                    "id": 3, 
                    "disabled_in_setter": true, 
                    "name": "closed_secured"
                }, 
                {
                    "id": 4, 
                    "disabled_in_setter": true, 
                    "name": "open_secured"
                }, 
                {
                    "id": 5, 
                    "disabled_in_setter": true, 
                    "name": "hard_top_mounted"
                }, 
                {
                    "id": 6, 
                    "disabled_in_setter": true, 
                    "name": "intermediate_position"
                }, 
                {
                    "id": 7, 
                    "disabled_in_setter": true, 
                    "name": "loading_position"
                }, 
                {
                    "id": 8, 
                    "disabled_in_setter": true, 
                    "name": "loading_position_immediate"
                }
            ], 
            "size": 1, 
            "type": "enum", 
            "id": 3, 
            "examples": [
                {
                    "hex": "01", 
                    "description": "Convertible roof is open", 
                    "value": "open"
                }
            ]
        }, 
        {
            "name": "sunroof_tilt_state", 
            "name_cased": "sunroofTiltState", 
            "enum_values": [
                {
                    "verb": "close", 
                    "id": 0, 
                    "name": "closed"
                }, 
                {
                    "id": 1, 
                    "name": "tilted"
                }, 
                {
                    "id": 2, 
                    "name": "half_tilted"
                }
            ], 
            "size": 1, 
            "type": "enum", 
            "id": 4, 
            "examples": [
                {
                    "hex": "02", 
                    "description": "Sunroof is half-tilted", 
                    "value": "half_tilted"
                }
            ]
        }, 
        {
            "name": "sunroof_state", 
            "name_cased": "sunroofState", 
            "enum_values": [
                {
                    "verb": "close", 
                    "id": 0, 
                    "name": "closed"
                }, 
                {
                    "id": 1, 
                    "name": "open"
                }, 
                {
                    "id": 2, 
                    "name": "intermediate"
                }
            ], 
            "size": 1, 
            "type": "enum", 
            "id": 5, 
            "examples": [
                {
                    "hex": "01", 
                    "description": "Sunroof is open", 
                    "value": "open"
                }
            ]
        }
    ], 
    "setters": [
        {
            "optional": [
                1, 
                2, 
                3, 
                4, 
                5
            ], 
            "name": "control_rooftop"
        }
    ]
}